LICENSE
MANIFEST.in
README.rst
setup.cfg
setup.py
versioneer.py
tpDcc/__init__.py
tpDcc/dccs/__init__.py
tpDcc/dccs/standalone/__init__.py
tpDcc/dccs/standalone/__logging__.ini
tpDcc/dccs/standalone/__version__.py
tpDcc/dccs/standalone/_version.py
tpDcc/dccs/standalone/dcc.py
tpDcc_dccs_standalone.egg-info/PKG-INFO
tpDcc_dccs_standalone.egg-info/SOURCES.txt
tpDcc_dccs_standalone.egg-info/dependency_links.txt
tpDcc_dccs_standalone.egg-info/not-zip-safe
tpDcc_dccs_standalone.egg-info/requires.txt
tpDcc_dccs_standalone.egg-info/top_level.txt