Metadata-Version: 2.1
Name: tpDcc-dccs-standalone
Version: 0.0.1
Summary: Standalone implementation for tpDcc.
Home-page: https://github.com/tpDcc/tpDcc-dccs-standalone
Author: Tomas Poveda
Author-email: tpovedatd@gmail.com
License: MIT
Platform: UNKNOWN
Provides-Extra: dev
Provides-Extra: test
